dunk/__init__.py
dunk/dunk.py
dunk/renderables.py
dunk/underline_bar.py
dunk-0.5.0b0.dist-info/METADATA
dunk-0.5.0b0.dist-info/WHEEL
dunk-0.5.0b0.dist-info/entry_points.txt
dunk-0.5.0b0.dist-info/licenses/LICENSE
dunk-0.5.0b0.dist-info/RECORD
