Metadata-Version: 2.4
Name: dunk
Version: 0.5.0b0
Summary: Beautiful side-by-side diffs in your terminal
Project-URL: homepage, https://github.com/darrenburns/dunk
Project-URL: repository, https://github.com/darrenburns/dunk
Project-URL: issues, https://github.com/darrenburns/dunk/issues
Project-URL: documentation, https://github.com/darrenburns/dunk/blob/main/README.md
Author-email: Darren Burns <darrenb900@gmail.com>
License: Copyright (c) 2025 Darren Burns
License-File: LICENSE
Keywords: cli,dev-tools,diff,git,side-by-side,terminal
Classifier: Environment :: Console
Classifier: Intended Audience :: Developers
Classifier: License :: OSI Approved :: MIT License
Classifier: Programming Language :: Python :: 3
Classifier: Programming Language :: Python :: 3.11
Classifier: Programming Language :: Python :: 3.12
Classifier: Programming Language :: Python :: 3.13
Classifier: Programming Language :: Python :: 3.14
Requires-Python: >=3.11
Requires-Dist: rich>=12.1.0
Requires-Dist: unidiff>=0.7
